web_hacker/__init__.py
web_hacker/config.py
web_hacker/cdp/__init__.py
web_hacker/cdp/cdp_session.py
web_hacker/cdp/connection.py
web_hacker/cdp/interaction_monitor.py
web_hacker/cdp/network_monitor.py
web_hacker/cdp/storage_monitor.py
web_hacker/cdp/window_property_monitor.py
web_hacker/data_models/__init__.py
web_hacker/data_models/benchmarks.py
web_hacker/data_models/ui_elements.py
web_hacker/data_models/ui_interaction.py
web_hacker/data_models/window_property.py
web_hacker/data_models/routine/__init__.py
web_hacker/data_models/routine/dev_routine.py
web_hacker/data_models/routine/endpoint.py
web_hacker/data_models/routine/execution.py
web_hacker/data_models/routine/operation.py
web_hacker/data_models/routine/parameter.py
web_hacker/data_models/routine/placeholder.py
web_hacker/data_models/routine/routine.py
web_hacker/data_models/routine_discovery/llm_responses.py
web_hacker/data_models/routine_discovery/message.py
web_hacker/routine_discovery/__init__.py
web_hacker/routine_discovery/agent.py
web_hacker/routine_discovery/context_manager.py
web_hacker/scripts/__init__.py
web_hacker/scripts/browser_monitor.py
web_hacker/scripts/discover_routine.py
web_hacker/scripts/execute_routine.py
web_hacker/scripts/run_benchmarks.py
web_hacker/sdk/__init__.py
web_hacker/sdk/client.py
web_hacker/sdk/discovery.py
web_hacker/sdk/execution.py
web_hacker/sdk/monitor.py
web_hacker/utils/__init__.py
web_hacker/utils/data_utils.py
web_hacker/utils/exceptions.py
web_hacker/utils/infra_utils.py
web_hacker/utils/js_utils.py
web_hacker/utils/llm_utils.py
web_hacker/utils/logger.py
web_hacker/utils/terminal_utils.py
web_hacker/utils/web_socket_utils.py
web_hacker-1.2.3.dist-info/METADATA
web_hacker-1.2.3.dist-info/WHEEL
web_hacker-1.2.3.dist-info/entry_points.txt
web_hacker-1.2.3.dist-info/licenses/LICENSE
web_hacker-1.2.3.dist-info/RECORD
