Metadata-Version: 2.4
Name: web-hacker
Version: 1.2.3
Summary: SDK for reverse engineering web apps
Project-URL: Homepage, https://www.vectorly.app
Project-URL: Documentation, https://github.com/VectorlyApp/web-hacker#readme
Project-URL: Repository, https://github.com/VectorlyApp/web-hacker
Project-URL: Issues, https://github.com/VectorlyApp/web-hacker/issues
Author-email: Vectorly <contact@vectorly.app>
License: Apache-2.0
License-File: LICENSE
Keywords: api-discovery,automation,browser-automation,cdp,chrome-devtools,reverse-engineering,sdk,web-scraping
Classifier: Development Status :: 4 - Beta
Classifier: Intended Audience :: Developers
Classifier: License :: OSI Approved :: Apache Software License
Classifier: Programming Language :: Python :: 3
Classifier: Programming Language :: Python :: 3.12
Classifier: Topic :: Internet :: WWW/HTTP :: Browsers
Classifier: Topic :: Software Development :: Libraries :: Python Modules
Classifier: Topic :: Software Development :: Testing
Requires-Python: <3.13,>=3.12.3
Requires-Dist: beautifulsoup4>=4.14.2
Requires-Dist: jmespath<2,>=1.0.1
Requires-Dist: openai>=2.6.1
Requires-Dist: pydantic>=2.11.4
Requires-Dist: pylint>=3.0.0
Requires-Dist: pytest>=8.3.5
Requires-Dist: python-dotenv>=1.2.1
Requires-Dist: requests>=2.31.0
Requires-Dist: tldextract>=5.1.0
Requires-Dist: toonify[pydantic]>=1.5.1
Requires-Dist: websocket-client>=1.6.0
Requires-Dist: websockets>=15.0.1
Provides-Extra: dev
Requires-Dist: ipykernel>=6.29.5; extra == 'dev'
